huaweicloudsdkcpts/__init__.py
huaweicloudsdkcpts/v1/__init__.py
huaweicloudsdkcpts/v1/cpts_async_client.py
huaweicloudsdkcpts/v1/cpts_client.py
huaweicloudsdkcpts/v1/model/__init__.py
huaweicloudsdkcpts/v1/model/agent_config.py
huaweicloudsdkcpts/v1/model/aw_info_dto.py
huaweicloudsdkcpts/v1/model/batch_update_task_status_request.py
huaweicloudsdkcpts/v1/model/batch_update_task_status_request_body.py
huaweicloudsdkcpts/v1/model/batch_update_task_status_response.py
huaweicloudsdkcpts/v1/model/batch_update_task_status_response_body_result.py
huaweicloudsdkcpts/v1/model/brand_brokens.py
huaweicloudsdkcpts/v1/model/broken_list.py
huaweicloudsdkcpts/v1/model/case_aw_info.py
huaweicloudsdkcpts/v1/model/case_doc.py
huaweicloudsdkcpts/v1/model/case_doc_steps.py
huaweicloudsdkcpts/v1/model/case_info_detail.py
huaweicloudsdkcpts/v1/model/case_report_detail.py
huaweicloudsdkcpts/v1/model/case_report_detail_result.py
huaweicloudsdkcpts/v1/model/case_report_details.py
huaweicloudsdkcpts/v1/model/case_report_summary.py
huaweicloudsdkcpts/v1/model/code_message_resq.py
huaweicloudsdkcpts/v1/model/content.py
huaweicloudsdkcpts/v1/model/content_header.py
huaweicloudsdkcpts/v1/model/content_info.py
huaweicloudsdkcpts/v1/model/contents.py
huaweicloudsdkcpts/v1/model/core_index.py
huaweicloudsdkcpts/v1/model/crease_case_response_json.py
huaweicloudsdkcpts/v1/model/create_case_request.py
huaweicloudsdkcpts/v1/model/create_case_request_body.py
huaweicloudsdkcpts/v1/model/create_case_response.py
huaweicloudsdkcpts/v1/model/create_case_result_json.py
huaweicloudsdkcpts/v1/model/create_directory_request.py
huaweicloudsdkcpts/v1/model/create_directory_request_body.py
huaweicloudsdkcpts/v1/model/create_directory_response.py
huaweicloudsdkcpts/v1/model/create_new_case_request.py
huaweicloudsdkcpts/v1/model/create_new_case_response.py
huaweicloudsdkcpts/v1/model/create_new_task_request.py
huaweicloudsdkcpts/v1/model/create_new_task_response.py
huaweicloudsdkcpts-3.1.184.dist-info/METADATA
huaweicloudsdkcpts-3.1.184.dist-info/WHEEL
huaweicloudsdkcpts-3.1.184.dist-info/licenses/LICENSE
huaweicloudsdkcpts-3.1.184.dist-info/RECORD
